{"guide_using_tutorials_install.md":"ChHlub2p","guide_functions_system_setting.md":"Cw7TvLcQ","zh_guide_other_contact_group.md":"CPHmyvUS","guide_functions_navigate_current_api.md":"pRqeqCNu","zh_guide_functions_global_setting.md":"2eW0iXSd","guide_functions_global_setting.md":"CkMSKObd","zh_index.md":"D2vuVhud","zh_guide_functions_api_tree.md":"Bseuiuro","guide_other_contact_group.md":"wmjKTf8F","zh_guide_introduction_what.md":"vCwCtStr","zh_guide_functions_clear_all.md":"CctaCsnv","guide_functions_clear_all.md":"DjSUxpvy","index.md":"CZ_gkDCs","zh_guide_functions_system_setting.md":"42M5xSzm","guide_functions_trigger_timer.md":"CMwjM_Jl","zh_guide_using_tutorials_install.md":"D8Fr7-Jb","guide_using_tutorials_getting_started.md":"DNyxhj7B","zh_guide_functions_history_request_record.md":"iu7yHdmS","zh_guide_functions_curl_export.md":"SxOjO7T7","zh_guide_functions_navigate_current_api.md":"BmzTxsg_","guide_functions_history_request_record.md":"DGrp_5k9","zh_guide_functions_saved_request_record.md":"DTXfVuYA","guide_other_faq.md":"CCYN9MY_","guide_functions_search_api.md":"DjvYZ2BI","guide_functions_curl_export.md":"uWW7lzl3","zh_guide_using_tutorials_getting_started.md":"CknKLJUV","zh_guide_functions_trigger_timer.md":"DWAGBovq","guide_functions_api_tree.md":"cl30PiaK","guide_functions_saved_request_record.md":"QF-wNhhc","zh_guide_functions_search_api.md":"DWnakqOz","zh_guide_functions_environments.md":"B_0bhRtW","guide_functions_environments.md":"CC3Imp3Q","zh_guide_other_faq.md":"DPU5JDZT","guide_introduction_what.md":"0t-BWKJ_"}
